pystealth/__init__.py
pystealth/pystealth.py
pystealth-1.0.0.dist-info/LICENSE
pystealth-1.0.0.dist-info/METADATA
pystealth-1.0.0.dist-info/WHEEL
pystealth-1.0.0.dist-info/top_level.txt
pystealth-1.0.0.dist-info/RECORD
