Metadata-Version: 2.1
Name: pystealth
Version: 1.0.0
Summary: Python module for preventing detection of CDP in Selenium, Puppeteer, and Playwright.
Home-page: https://github.com/DedInc/pystealth
Author: Maehdakvan
Author-email: visitanimation@google.com
Project-URL: Bug Tracker, https://github.com/DedInc/pystealth/issues
Classifier: Programming Language :: Python :: 3
Classifier: License :: OSI Approved :: MIT License
Classifier: Operating System :: OS Independent
Requires-Python: >=3.6
License-File: LICENSE
